bundesliga_tippspiel/Config.py
bundesliga_tippspiel/__init__.py
bundesliga_tippspiel/enums.py
bundesliga_tippspiel/exceptions.py
bundesliga_tippspiel/jinja_extras.py
bundesliga_tippspiel/main.py
bundesliga_tippspiel/template_extras.py
bundesliga_tippspiel/background/__init__.py
bundesliga_tippspiel/background/openligadb.py
bundesliga_tippspiel/background/pointscalc.py
bundesliga_tippspiel/background/reminders.py
bundesliga_tippspiel/background/season_events.py
bundesliga_tippspiel/db/SeasonEvent.py
bundesliga_tippspiel/db/__init__.py
bundesliga_tippspiel/db/match_data/Goal.py
bundesliga_tippspiel/db/match_data/Match.py
bundesliga_tippspiel/db/match_data/Player.py
bundesliga_tippspiel/db/match_data/Team.py
bundesliga_tippspiel/db/match_data/__init__.py
bundesliga_tippspiel/db/settings/DisplayBotsSettings.py
bundesliga_tippspiel/db/settings/ReminderSettings.py
bundesliga_tippspiel/db/settings/__init__.py
bundesliga_tippspiel/db/user_generated/Bet.py
bundesliga_tippspiel/db/user_generated/ChatMessage.py
bundesliga_tippspiel/db/user_generated/LeaderboardEntry.py
bundesliga_tippspiel/db/user_generated/MatchdayWinner.py
bundesliga_tippspiel/db/user_generated/SeasonWinner.py
bundesliga_tippspiel/db/user_generated/UserProfile.py
bundesliga_tippspiel/db/user_generated/__init__.py
bundesliga_tippspiel/routes/__init__.py
bundesliga_tippspiel/routes/betting.py
bundesliga_tippspiel/routes/chat.py
bundesliga_tippspiel/routes/info.py
bundesliga_tippspiel/routes/settings.py
bundesliga_tippspiel/routes/stats.py
bundesliga_tippspiel/routes/tables.py
bundesliga_tippspiel/routes/api/__init__.py
bundesliga_tippspiel/routes/api/betting.py
bundesliga_tippspiel/routes/api/info.py
bundesliga_tippspiel/static/package.json
bundesliga_tippspiel/static/images/background.jpg
bundesliga_tippspiel/static/images/logo.png
bundesliga_tippspiel/static/images/dependencies/bulma-logo.png
bundesliga_tippspiel/static/images/dependencies/flask-logo.png
bundesliga_tippspiel-2.0.10.dist-info/LICENSE
bundesliga_tippspiel-2.0.10.dist-info/METADATA
bundesliga_tippspiel-2.0.10.dist-info/WHEEL
bundesliga_tippspiel-2.0.10.dist-info/top_level.txt
bundesliga_tippspiel-2.0.10.dist-info/RECORD
