Metadata-Version: 2.1
Name: bundesliga-tippspiel
Version: 2.0.10
Summary: A Bundesliga Tippspiel Website
Home-page: https://gitlab.namibsun.net/namibsun/python/bundesliga-tippspiel
Author: Hermann Krumrey
Author-email: hermann@krumreyh.com
License: GNU GPL3
Platform: UNKNOWN
Classifier: License :: OSI Approved :: GNU General Public License v3 (GPLv3)
License-File: LICENSE
Requires-Dist: flask
Requires-Dist: flask-login
Requires-Dist: flask-sqlalchemy
Requires-Dist: requests
Requires-Dist: blinker
Requires-Dist: sentry-sdk
Requires-Dist: sqlalchemy
Requires-Dist: werkzeug
Requires-Dist: cherrypy
Requires-Dist: puffotter[crypto]
Requires-Dist: beautifulsoup4
Requires-Dist: pytz
Requires-Dist: jerrycan (>=0.3.2)
